setup.py
client/__init__.py
client/client.py
client/client_dir/__init__.py
client/client_dir/add_contact.py
client/client_dir/client_database.py
client/client_dir/del_contact.py
client/client_dir/main_window.py
client/client_dir/main_window_conv.py
client/client_dir/start_dialog.py
client/client_dir/transport.py
client/common/__init__.py
client/common/decorators.py
client/common/descriptors.py
client/common/errors.py
client/common/metaclasses.py
client/common/utils.py
client/common/variables.py
client/doc/__init__.py
client/doc/source/__init__.py
client/doc/source/conf.py
client/log/__init__.py
client/log/config/__init__.py
client/log/config/client_log_config.py
client/log/config/server_log_config.py
client/unit_tests/__init__.py
messenger_client_may.egg-info/PKG-INFO
messenger_client_may.egg-info/SOURCES.txt
messenger_client_may.egg-info/dependency_links.txt
messenger_client_may.egg-info/requires.txt
messenger_client_may.egg-info/top_level.txt