Metadata-Version: 2.1
Name: messenger-client-may
Version: 0.9.1
Summary: client packet
Home-page: UNKNOWN
Author: Egor Varlamov
License: UNKNOWN
Platform: UNKNOWN
